[
 {
  "allcount": 344
 },
 {
  "title": "大学ぼっちが異世界平定",
  "ncode": "N8812FX"
 },
 {
  "title": "七行詩　611.~620.",
  "ncode": "N8527FY"
 },
 {
  "title": "武士道は貫くものじゃ無い",
  "ncode": "N2154FZ"
 },
 {
  "title": "遊具とランナーと飲み屋街",
  "ncode": "N2282FZ"
 },
 {
  "title": "死神辺境伯と死にたがり殿下",
  "ncode": "N2597FZ"
 },
 {
  "title": "悪役令嬢で何が悪い！？　",
  "ncode": "N2817FZ"
 },
 {
  "title": "『小説家になろう』の全作品の週別ユニークユーザ数を集計して分析してみた（2019年12月31日時点）【省エネ版】",
  "ncode": "N2818FZ"
 },
 {
  "title": "そこに力があるから華が咲く  〜なんてカッコつけてみただけの話〜",
  "ncode": "N2819FZ"
 },
 {
  "title": "闇の世界で",
  "ncode": "N2827FZ"
 },
 {
  "title": "酢橘(すだち)",
  "ncode": "N2828FZ"
 },
 {
  "title": "アッザムは飛んでいく",
  "ncode": "N2829FZ"
 },
 {
  "title": "転生したのはいいけど、敵側！？",
  "ncode": "N2831FZ"
 },
 {
  "title": "フタリマジョ　アルファバージョン",
  "ncode": "N2832FZ"
 },
 {
  "title": "女神と魔王は愛を知りました",
  "ncode": "N2834FZ"
 },
 {
  "title": "ヒカリ",
  "ncode": "N2837FZ"
 },
 {
  "title": "鏡【短編】",
  "ncode": "N2838FZ"
 },
 {
  "title": "感想を書く読者様に問いたい事、考えて欲しい事",
  "ncode": "N2840FZ"
 },
 {
  "title": "赤ずきんの幸せ計画",
  "ncode": "N2575FZ"
 },
 {
  "title": "海とぼくらとマドンナ(人魚姫)と",
  "ncode": "N2845FZ"
 },
 {
  "title": "敵を殺してる間だけはこの世界がとても楽しい",
  "ncode": "N2846FZ"
 },
 {
  "title": "宇宙宅配便の配達日時指定",
  "ncode": "N2847FZ"
 },
 {
  "title": "スターウォーズ EP8のサブタイトルが「最後のジェダイ」だと知った時点で考えていたもの",
  "ncode": "N2848FZ"
 },
 {
  "title": "恐らく、多分、これが黒歴史というモノになるのだが、それはもう少しあとの話。",
  "ncode": "N2852FZ"
 },
 {
  "title": "剣",
  "ncode": "N2854FZ"
 },
 {
  "title": "僕はミステリ作家が嫌いだ",
  "ncode": "N2855FZ"
 },
 {
  "title": "炭焼きの煙に涙ぐみながら、九十九折の山道を登っていく　2話",
  "ncode": "N2859FZ"
 },
 {
  "title": "茜さす君に見初むる幸ありて。",
  "ncode": "N2860FZ"
 },
 {
  "title": "異世界金属を削るには？",
  "ncode": "N2864FZ"
 },
 {
  "title": "転生？します。",
  "ncode": "N2868FZ"
 },
 {
  "title": "ミヨアラズム",
  "ncode": "N2869FZ"
 },
 {
  "title": "俺を笑わさないとここの商品を買えないよ！",
  "ncode": "N2429FZ"
 },
 {
  "title": "銀色に嘆く世界で",
  "ncode": "N2871FZ"
 },
 {
  "title": "愛。",
  "ncode": "N2870FZ"
 },
 {
  "title": "恋",
  "ncode": "N2872FZ"
 },
 {
  "title": "やっぱ評価ポイントは入れなくていいです……",
  "ncode": "N2873FZ"
 },
 {
  "title": "いつのまにか異世界転移～盲目の杖術師～",
  "ncode": "N2875FZ"
 },
 {
  "title": "４コマ小説「右手の不気味な黒い影」",
  "ncode": "N2878FZ"
 },
 {
  "title": "これは転生なのか？ちがうのか？",
  "ncode": "N2880FZ"
 },
 {
  "title": "次回予告",
  "ncode": "N3509FX"
 },
 {
  "title": "ランカーゼロ",
  "ncode": "N2853FZ"
 },
 {
  "title": "虹のふもと",
  "ncode": "N2884FZ"
 },
 {
  "title": "複製される私たち　完結編",
  "ncode": "N2886FZ"
 },
 {
  "title": "『精霊に嫌われた』エルフと『聖霊に愛された』妹（仮）エルフの幻想世界英雄譚",
  "ncode": "N2732FZ"
 },
 {
  "title": "ファンタジーは知らない",
  "ncode": "N2861FZ"
 },
 {
  "title": "ことば。",
  "ncode": "N2876FZ"
 },
 {
  "title": "魔法を集めながら冒険者生活",
  "ncode": "N2877FZ"
 },
 {
  "title": "Happy new Yeah!",
  "ncode": "N2892FZ"
 },
 {
  "title": "記憶の扉",
  "ncode": "N2894FZ"
 },
 {
  "title": "令嬢の婚活？",
  "ncode": "N2888FZ"
 },
 {
  "title": "化け物×異世界",
  "ncode": "N2863FZ"
 },
 {
  "title": "記録者不在につき、自動筆記開始…",
  "ncode": "N2893FZ"
 },
 {
  "title": "刻印",
  "ncode": "N2899FZ"
 },
 {
  "title": "不思議な夢",
  "ncode": "N2904FZ"
 },
 {
  "title": "異世界はご都合主義だと悟った勇者の末路",
  "ncode": "N2905FZ"
 },
 {
  "title": "ライバル令嬢は悪役令嬢ではございません。",
  "ncode": "N2830FZ"
 },
 {
  "title": "何時か逢いに行くから",
  "ncode": "N2906FZ"
 },
 {
  "title": "僕はどうやら異世界で魔法使い（女）になったようです…。",
  "ncode": "N2909FZ"
 },
 {
  "title": "替わらないココロ",
  "ncode": "N2910FZ"
 },
 {
  "title": "【STG】狙撃手のβプレイ",
  "ncode": "N2911FZ"
 },
 {
  "title": "虹が出てる間に",
  "ncode": "N2914FZ"
 },
 {
  "title": "ヒューマンの会",
  "ncode": "N2915FZ"
 },
 {
  "title": "恋する人へ",
  "ncode": "N2916FZ"
 },
 {
  "title": "Flat/Jumble",
  "ncode": "N2919FZ"
 },
 {
  "title": "3年D組 サツジン×キョウシツ  ",
  "ncode": "N2920FZ"
 },
 {
  "title": "侯爵令嬢の婚約〈連載版〉",
  "ncode": "N1863FZ"
 },
 {
  "title": "ひとつ、はきだした。",
  "ncode": "N2167FZ"
 },
 {
  "title": "いろいろおかしい小学校で日常生活送ってます",
  "ncode": "N2921FZ"
 },
 {
  "title": "引きこもりの花ヶ咲桜子は静かに語る。",
  "ncode": "N2925FZ"
 },
 {
  "title": "『秘密を知られたからには死んでもらいます』と毎日僕を殺そうと会いに来るドジっ子と恋に落ちる話。",
  "ncode": "N2926FZ"
 },
 {
  "title": "柔らかいお姉ちゃん",
  "ncode": "N2927FZ"
 },
 {
  "title": "ダメダメ男の日常 連載だけど短編",
  "ncode": "N2930FZ"
 },
 {
  "title": "佐藤さん",
  "ncode": "N2933FZ"
 },
 {
  "title": "銀色の月と幸せのゴンドラ",
  "ncode": "N2935FZ"
 },
 {
  "title": "なろう小説とはコカ・コーラのようであると見つけたり",
  "ncode": "N2937FZ"
 },
 {
  "title": "Love1学生恋愛",
  "ncode": "N2939FZ"
 },
 {
  "title": "事業所名【神式会社『次元監査特務室　救援勇者部』】",
  "ncode": "N2940FZ"
 },
 {
  "title": "剣の行方",
  "ncode": "N2942FZ"
 },
 {
  "title": "背後の声",
  "ncode": "N2945FZ"
 },
 {
  "title": "堕ちた先はワンダーランドでした",
  "ncode": "N2947FZ"
 },
 {
  "title": "ゆとり世代に",
  "ncode": "N2949FZ"
 },
 {
  "title": "秘封倶楽部がカケラマスターを目指すようです（原作、東方人形劇）",
  "ncode": "N2951FZ"
 },
 {
  "title": "クリームソーダ",
  "ncode": "N2952FZ"
 },
 {
  "title": "Bitter&amp;White  chocolate 〜溶ける、その温度で。",
  "ncode": "N2954FZ"
 },
 {
  "title": "指切りしましょう。",
  "ncode": "N2959FZ"
 },
 {
  "title": "算盤を数えてみる",
  "ncode": "N2958FZ"
 },
 {
  "title": "そうの俺と鬱な私3",
  "ncode": "N2961FZ"
 },
 {
  "title": "誰しも一度は青春の森に迷う！！",
  "ncode": "N2962FZ"
 },
 {
  "title": "Mother Crasher",
  "ncode": "N2965FZ"
 },
 {
  "title": "私の幻聴",
  "ncode": "N2966FZ"
 },
 {
  "title": "バックパッカーの老人、化け物と出会う",
  "ncode": "N2973FZ"
 },
 {
  "title": "他人に興味の無い人間が婚約破棄されたら",
  "ncode": "N2883FZ"
 },
 {
  "title": "ブランク",
  "ncode": "N2980FZ"
 },
 {
  "title": "大罪人、神に頼まれ異世界へ",
  "ncode": "N2985FZ"
 },
 {
  "title": "渋谷スクランブル",
  "ncode": "N2988FZ"
 },
 {
  "title": "『There Will Never Be Another You　～ジャズ研 恋物語～』",
  "ncode": "N2993FZ"
 },
 {
  "title": "ナガハシの極振り経済学　〜日本の現状編〜",
  "ncode": "N2994FZ"
 },
 {
  "title": "履修E",
  "ncode": "N2990FZ"
 },
 {
  "title": "漏れ俺私　～俺ＳＵＧＥＥ！～",
  "ncode": "N3002FZ"
 },
 {
  "title": "ふるものや",
  "ncode": "N3004FZ"
 },
 {
  "title": "異世界系小説のチートめなサブキャラの物語(仮)",
  "ncode": "N3006FZ"
 },
 {
  "title": "召喚聖女は逞しく生きる",
  "ncode": "N3007FZ"
 },
 {
  "title": "朝日が眩しくも恋しい",
  "ncode": "N3008FZ"
 },
 {
  "title": "宝石の思い出と",
  "ncode": "N3009FZ"
 },
 {
  "title": "カンバスとカンツォーネ",
  "ncode": "N3014FZ"
 },
 {
  "title": "死神の高校生は魔法が使える世界で生きるそうです！",
  "ncode": "N3016FZ"
 },
 {
  "title": "東京時代",
  "ncode": "N3019FZ"
 },
 {
  "title": "ポケモンセンター先輩",
  "ncode": "N3026FZ"
 },
 {
  "title": "南極紛争(三章)",
  "ncode": "N3028FZ"
 },
 {
  "title": "トロッコ問題夢十夜",
  "ncode": "N2546FZ"
 },
 {
  "title": "にんげんかんけい",
  "ncode": "N3001FZ"
 },
 {
  "title": "ながみみせんせいとわたし",
  "ncode": "N3029FZ"
 },
 {
  "title": "空を　飛びたい",
  "ncode": "N3030FZ"
 },
 {
  "title": "芸人失格",
  "ncode": "N3032FZ"
 },
 {
  "title": "僕の平和な世の中のつくりかた～SSRウー婆ちゃんを狙え～重課金編(第1.5部)",
  "ncode": "N3034FZ"
 },
 {
  "title": "ナーロッパの明日の天気は晴れ。明後日も晴れです。",
  "ncode": "N3037FZ"
 },
 {
  "title": "僕の前の席の女の子",
  "ncode": "N3039FZ"
 },
 {
  "title": "【超短編】ミチオシエ",
  "ncode": "N3040FZ"
 },
 {
  "title": "意味がわかると若干怖いかもしれない話 -保安検査-",
  "ncode": "N3044FZ"
 },
 {
  "title": "天才的発明品を使ったら、秒で大魔王が配下になった件",
  "ncode": "N3045FZ"
 },
 {
  "title": "転生女神の御業",
  "ncode": "N3047FZ"
 },
 {
  "title": "「ごめんね」と「お疲れさま」甘いものでもどうぞ",
  "ncode": "N2176FZ"
 },
 {
  "title": "カーディナルコード",
  "ncode": "N3048FZ"
 },
 {
  "title": "マズ飯",
  "ncode": "N3050FZ"
 },
 {
  "title": "番人",
  "ncode": "N3051FZ"
 },
 {
  "title": "受験生に思う",
  "ncode": "N3053FZ"
 },
 {
  "title": "文字数は作品の面白さに影響するのか？",
  "ncode": "N3055FZ"
 },
 {
  "title": "仏の顔も三度まで",
  "ncode": "N3056FZ"
 },
 {
  "title": "悪魔狩り風来坊",
  "ncode": "N3057FZ"
 },
 {
  "title": "【超短編】人間になった猫",
  "ncode": "N3059FZ"
 },
 {
  "title": "魔王とよばれた男が生まれ変わってやりなおし",
  "ncode": "N2960FZ"
 },
 {
  "title": "幼馴染から恋人になったら彼が甘すぎてしんじゃいます！",
  "ncode": "N3069FZ"
 },
 {
  "title": "Pa『　』eT",
  "ncode": "N3063FZ"
 },
 {
  "title": "自民党はテンプレである。投票型ランキングと投票政治の類似性",
  "ncode": "N3070FZ"
 },
 {
  "title": "つらいよ",
  "ncode": "N3071FZ"
 },
 {
  "title": "勇者の聖剣",
  "ncode": "N3072FZ"
 },
 {
  "title": "ねねと私",
  "ncode": "N3074FZ"
 },
 {
  "title": "影虎の血刀（かげとらのけっとう）",
  "ncode": "N3075FZ"
 },
 {
  "title": "影の世界で",
  "ncode": "N3076FZ"
 },
 {
  "title": "バーベマの機械工",
  "ncode": "N3077FZ"
 },
 {
  "title": "夢心地",
  "ncode": "N3078FZ"
 },
 {
  "title": "嗚呼、愛しの魔王様",
  "ncode": "N3079FZ"
 },
 {
  "title": "極振り経済学　〜働きたくないでござる編〜",
  "ncode": "N3080FZ"
 },
 {
  "title": "使い魔の魔物娘達と主",
  "ncode": "N3081FZ"
 },
 {
  "title": "後ろ向き",
  "ncode": "N3082FZ"
 },
 {
  "title": "女の霊が毎晩一段ずつ階段を上がって来るので、とりあえず一段上に盛り塩してみた",
  "ncode": "N3083FZ"
 },
 {
  "title": "昔々ホントに昔のお話で",
  "ncode": "N3084FZ"
 },
 {
  "title": "さみしがり屋の私に。",
  "ncode": "N3089FZ"
 },
 {
  "title": "巻き込まれ体質の探偵と推理オタクの助手",
  "ncode": "N2971FZ"
 },
 {
  "title": "どうしてだろう",
  "ncode": "N3093FZ"
 },
 {
  "title": "身体強化は立派な魔法なので、やっぱり私も魔法使いです。（圧）",
  "ncode": "N2842FZ"
 },
 {
  "title": "未定",
  "ncode": "N3096FZ"
 },
 {
  "title": "私たちだけの二週間",
  "ncode": "N3099FZ"
 },
 {
  "title": "本物の勇者様",
  "ncode": "N3101FZ"
 },
 {
  "title": "俺は『しりとり』の呪いをかけられたのだ２",
  "ncode": "N3106FZ"
 },
 {
  "title": "第二の選択肢の世界線",
  "ncode": "N2773FZ"
 },
 {
  "title": "中国で流行している新型コロナウイルスをテレビが「危険ではない！」という事は、めちゃくちゃ危ない病気じゃないのか 中国からそういう風に言えと要請されているのか",
  "ncode": "N2907FZ"
 },
 {
  "title": "1/20【黒百合騎士のルーキーと非乖離的キャラメリゼ　※今回は読了10分と少し長めです】",
  "ncode": "N0788FZ"
 },
 {
  "title": "潮糸修繕　",
  "ncode": "N3091FZ"
 },
 {
  "title": "彼氏お金で買いました。",
  "ncode": "N3107FZ"
 },
 {
  "title": "ＷＯＲＬＤＷＡＬＫＥＲ～爆破武器所持少女と僕の英雄製作日記～",
  "ncode": "N2756FZ"
 },
 {
  "title": "住職探偵『メシアの雪郷』",
  "ncode": "N2874FZ"
 },
 {
  "title": "メリーさんは黒い羊",
  "ncode": "N3109FZ"
 },
 {
  "title": "ミリオンラーメンあいみすゆぅ",
  "ncode": "N3114FZ"
 },
 {
  "title": "異世界刑事劣情派（仮）",
  "ncode": "N3117FZ"
 },
 {
  "title": "彼女の猫に負けない",
  "ncode": "N3119FZ"
 },
 {
  "title": "ゼロ・ファイル　存在しない事件簿",
  "ncode": "N2929FZ"
 },
 {
  "title": "タイムカプセル",
  "ncode": "N2995FZ"
 },
 {
  "title": "実行太郎　－彼を止める術はないー",
  "ncode": "N3120FZ"
 },
 {
  "title": "天使のほほえみ",
  "ncode": "N2999FZ"
 },
 {
  "title": "狼少年になった悪役令嬢",
  "ncode": "N3121FZ"
 },
 {
  "title": "燃える令嬢、消す消防。同じ阿呆なら恋せにゃ損損っ！",
  "ncode": "N3122FZ"
 },
 {
  "title": "夢が",
  "ncode": "N3125FZ"
 },
 {
  "title": "distance",
  "ncode": "N3126FZ"
 },
 {
  "title": "異世界に行くのを断ってみたら天国だった件",
  "ncode": "N3128FZ"
 },
 {
  "title": "神とゴブリンと病院の卵(番外編)　ゴブリン編",
  "ncode": "N3085FZ"
 },
 {
  "title": "ファンタジー系学園ラブコメの世界に転生した が、どうやら脇役らしい",
  "ncode": "N2858FZ"
 },
 {
  "title": "やりすぎチュートリアル",
  "ncode": "N3132FZ"
 },
 {
  "title": "魔王が可愛くて辛い",
  "ncode": "N3134FZ"
 },
 {
  "title": "異世界転移したらゴブリンだったので、とりあえず世界征服を目指してみる。",
  "ncode": "N3139FZ"
 },
 {
  "title": "童貞勇者と淫魔なカノジョ　〜ユニークスキル《童貞特権》により、性的興奮で身体強化&amp;レベルUPする勇者。能力値は性欲に極振りで！？〜",
  "ncode": "N3143FZ"
 },
 {
  "title": "二〇二〇年のラストリゾート",
  "ncode": "N3145FZ"
 },
 {
  "title": "我が姫様と五令嬢、凶暴につき",
  "ncode": "N3146FZ"
 },
 {
  "title": "リアルで努力チートしてみた結果ハーレムが実現した",
  "ncode": "N3147FZ"
 },
 {
  "title": "ファンタジー世界にTS転生したらどう生きるか？",
  "ncode": "N3151FZ"
 },
 {
  "title": "道しるべ",
  "ncode": "N3155FZ"
 },
 {
  "title": "少年探偵久遠の探偵議事録",
  "ncode": "N3156FZ"
 },
 {
  "title": "ガラスの割れた鮮明な音",
  "ncode": "N3158FZ"
 },
 {
  "title": "シスコンではないけれど。",
  "ncode": "N3160FZ"
 },
 {
  "title": "【ステマ小説】小説：限りなく透明に近いブルー 編",
  "ncode": "N3161FZ"
 },
 {
  "title": "予想なんてあてにしちゃダメ",
  "ncode": "N3162FZ"
 },
 {
  "title": "怪しいイケメンくんと異世界旅行",
  "ncode": "N3163FZ"
 },
 {
  "title": "何かしら気づかないと",
  "ncode": "N3164FZ"
 },
 {
  "title": "教師島 -紗山優果編-",
  "ncode": "N3165FZ"
 },
 {
  "title": "リンカー喰らいと村娘A",
  "ncode": "N3171FZ"
 },
 {
  "title": "【百合にしてみた】故郷の小さな神社の境内、篝火の前、昔なじみの「親友」と。",
  "ncode": "N2908FZ"
 },
 {
  "title": "ワルツを踊る百合",
  "ncode": "N3173FZ"
 },
 {
  "title": "サー・ゲオルグ・ショルティの音楽的発露、村上春樹敵世界観の崩壊",
  "ncode": "N3174FZ"
 },
 {
  "title": "私は文章が下手",
  "ncode": "N3175FZ"
 },
 {
  "title": "『On Green Dolphin Street　～ジャズ研 恋物語～』",
  "ncode": "N3180FZ"
 },
 {
  "title": "大河ドラマ『麒麟がくる』を観て、気づいたことをメモしていく。",
  "ncode": "N3183FZ"
 },
 {
  "title": "もしもし　情報屋　ですが？【仮タイトル】",
  "ncode": "N3092FZ"
 },
 {
  "title": "すごい腕前を持つ美しい女剣士が消えた話４",
  "ncode": "N3185FZ"
 },
 {
  "title": "秋葉原ヲタク白書53 神田石鹸ノ国奇譚",
  "ncode": "N3187FZ"
 },
 {
  "title": "素晴らしき世界",
  "ncode": "N3188FZ"
 },
 {
  "title": "吟遊詩人と麦の町",
  "ncode": "N3191FZ"
 },
 {
  "title": "未来に進むために",
  "ncode": "N3192FZ"
 },
 {
  "title": "南の島の小さな奇跡",
  "ncode": "N3195FZ"
 },
 {
  "title": "本編番外編とその他の世界線",
  "ncode": "N2779FZ"
 },
 {
  "title": "サンダーソニア",
  "ncode": "N3196FZ"
 },
 {
  "title": "プラネテリア",
  "ncode": "N3197FZ"
 },
 {
  "title": "記念すべき５００回目の異世界転生です！",
  "ncode": "N3199FZ"
 },
 {
  "title": "クラスメイトのあの子は天使の羽をもっている",
  "ncode": "N3100FZ"
 },
 {
  "title": "叶わない",
  "ncode": "N3200FZ"
 },
 {
  "title": "炎の先導者と運命の救世主",
  "ncode": "N3186FZ"
 },
 {
  "title": "たにぐっち",
  "ncode": "N3204FZ"
 },
 {
  "title": "夢の話",
  "ncode": "N3207FZ"
 },
 {
  "title": "救えない青と降り続ける羽",
  "ncode": "N3208FZ"
 },
 {
  "title": "たましい　～コミュ障ゲームオタはチョロいけど気になる茶髪ギャルの為に頑張ろうと思います～",
  "ncode": "N3211FZ"
 },
 {
  "title": "スマホおたくの事件簿",
  "ncode": "N3168FZ"
 },
 {
  "title": "異世界に転生したらチートになれるかな？",
  "ncode": "N3215FZ"
 },
 {
  "title": "chara make(キャラ メイク)",
  "ncode": "N3220FZ"
 },
 {
  "title": "二羽の小鳥",
  "ncode": "N3221FZ"
 },
 {
  "title": "平凡な男と非凡なクラスメート　～四コマ小説～",
  "ncode": "N3223FZ"
 },
 {
  "title": "②「黒の流星」",
  "ncode": "N3225FZ"
 },
 {
  "title": "意味怖風味",
  "ncode": "N3228FZ"
 },
 {
  "title": "いつわりのメイリア",
  "ncode": "N3229FZ"
 },
 {
  "title": "はたらきたくないやつらのひとりごと",
  "ncode": "N3230FZ"
 },
 {
  "title": "JKが勇者召喚で死んだので異世界に転生するそうです。",
  "ncode": "N3240FZ"
 },
 {
  "title": "自由な将来",
  "ncode": "N3241FZ"
 },
 {
  "title": "愛犬テリー　～僕の相棒と家族の物語～　",
  "ncode": "N3222FZ"
 },
 {
  "title": "即興小説#313 実験体の魚",
  "ncode": "N3246FZ"
 },
 {
  "title": "アマラ",
  "ncode": "N3252FZ"
 },
 {
  "title": "エクソシストは職業欄になんて書けばいい？",
  "ncode": "N3169FZ"
 },
 {
  "title": "中2病が書いた自伝的なやつ　(読みずらいためもし読む人は注意) ",
  "ncode": "N3254FZ"
 },
 {
  "title": "形而上学",
  "ncode": "N3256FZ"
 },
 {
  "title": "花のアリスと金の鷲",
  "ncode": "N3259FZ"
 },
 {
  "title": "僕とAIの愉快な旅路",
  "ncode": "N3260FZ"
 },
 {
  "title": "切り捨て御免",
  "ncode": "N3018FZ"
 },
 {
  "title": "夢想噺",
  "ncode": "N2938FZ"
 },
 {
  "title": "未来戦争",
  "ncode": "N2843FZ"
 },
 {
  "title": "クレノイレ",
  "ncode": "N2976FZ"
 },
 {
  "title": "異能管理局、即応班(パシリ班)/班員→バカ、バカ(美少女)、遅刻魔、そして俺…",
  "ncode": "N0296FZ"
 },
 {
  "title": "人生は娯楽や",
  "ncode": "N3095FZ"
 },
 {
  "title": "受験日記　",
  "ncode": "N3181FZ"
 },
 {
  "title": "聖女の召喚",
  "ncode": "N2997FZ"
 },
 {
  "title": "桜舞い散る丘で",
  "ncode": "N3189FZ"
 },
 {
  "title": "美女と珍獣",
  "ncode": "N2992FZ"
 },
 {
  "title": "嘘つき魔女と太陽の子",
  "ncode": "N2879FZ"
 },
 {
  "title": "炎の追憶",
  "ncode": "N3104FZ"
 },
 {
  "title": "明日、君に殺されたい。",
  "ncode": "N3058FZ"
 },
 {
  "title": "〈NJG〉 ニュートンとジャンヌ・ダルクがゲームを救う話",
  "ncode": "N2913FZ"
 },
 {
  "title": "ソードワールドTRPGリプレイ　～狼少年はさかまく螺旋の少女に出会う～",
  "ncode": "N3137FZ"
 },
 {
  "title": "ライ",
  "ncode": "N3239FZ"
 },
 {
  "title": "魔王が間違って召喚された俺で大丈夫だろうか？",
  "ncode": "N3249FZ"
 },
 {
  "title": "春夏秋冬・焔",
  "ncode": "N2815FZ"
 },
 {
  "title": "cancer",
  "ncode": "N3013FZ"
 },
 {
  "title": "カミサマは管理人",
  "ncode": "N2850FZ"
 },
 {
  "title": "妹が絶対に負けないラブコメ",
  "ncode": "N2956FZ"
 },
 {
  "title": "『夢だと思った世界が、本当の世界でした。』",
  "ncode": "N2989FZ"
 },
 {
  "title": "Rebellion: オマケだったので反逆者になります。",
  "ncode": "N3150FZ"
 },
 {
  "title": "T氏、或いはK伯爵の百年の眠り",
  "ncode": "N3253FZ"
 },
 {
  "title": "【短編】ピタゴラなスイッチで高速円舞曲を一曲",
  "ncode": "N3124FZ"
 },
 {
  "title": "偏差値38の高校中退男は慶應大学を目指す",
  "ncode": "N2931FZ"
 },
 {
  "title": "メガじーちゃんはサイボーグ！？",
  "ncode": "N2895FZ"
 },
 {
  "title": "フィリピン放浪記",
  "ncode": "N2979FZ"
 },
 {
  "title": "河童太郎、大陸を往く",
  "ncode": "N3242FZ"
 },
 {
  "title": "断章　第二十二部",
  "ncode": "N2936FZ"
 },
 {
  "title": "未来が分かる人",
  "ncode": "N3012FZ"
 },
 {
  "title": "SとNのタペストリー",
  "ncode": "N3098FZ"
 },
 {
  "title": "１レベル冒険者が頑張るお話",
  "ncode": "N2722FZ"
 },
 {
  "title": "美味しいお話 いただきます",
  "ncode": "N3073FZ"
 },
 {
  "title": "三雄激突～英雄・悪党・元捕虜～",
  "ncode": "N3066FZ"
 },
 {
  "title": "ぐーたら男の異世界生活〜スマホを添えて〜",
  "ncode": "N3088FZ"
 },
 {
  "title": "【連載版だー！】ガチャ転生　〜ガチャで手に入れたスキルで異世界を楽しむ〜",
  "ncode": "N2618FZ"
 },
 {
  "title": "幼馴染みが寿勇者させようとしてきます",
  "ncode": "N3036FZ"
 },
 {
  "title": "私はこの戦場で戦っていきます。",
  "ncode": "N3198FZ"
 },
 {
  "title": "死んでまでいじめられた僕は乙女ゲームで美少女になってイケメン達に復讐する",
  "ncode": "N3022FZ"
 },
 {
  "title": "ボッチなのに縁切り神（美少女）に祟られました",
  "ncode": "N9534FY"
 },
 {
  "title": "お局希望のOLはさとりと共に",
  "ncode": "N3142FZ"
 },
 {
  "title": "ニートな僕の人生のやり直し",
  "ncode": "N3102FZ"
 },
 {
  "title": "食べる物がないからアレ食べたら人生180°変わっていきなりモテ始めたんですけど....",
  "ncode": "N3243FZ"
 },
 {
  "title": "笑いで千年戦争の決着を！　～三人の英雄と魔法の杖！？　異世界アウトバラエティ♪～",
  "ncode": "N3135FZ"
 },
 {
  "title": "臆病者の異世界転生記",
  "ncode": "N3157FZ"
 },
 {
  "title": "おかしなヤツでいっぱい",
  "ncode": "N3217FZ"
 },
 {
  "title": "ちょろすぎるツンデレ美少女が売れっ子漫画家で、嘘つきな俺がアシスタントな件について",
  "ncode": "N3184FZ"
 },
 {
  "title": "イマジナリー・ガールフレンド",
  "ncode": "N3248FZ"
 },
 {
  "title": "なろうファンタジーがクッソつまらないから本屋でファンタジー小説買ったらクッソつまらないなろうファンタジーだった件〜ブクマが軒並みクソながタイトルで草も生えない〜",
  "ncode": "N3218FZ"
 },
 {
  "title": "平穏な生活がしたい",
  "ncode": "N0624FZ"
 },
 {
  "title": "能力「書奪」は異世界最強でした",
  "ncode": "N3238FZ"
 },
 {
  "title": "人生最後の日、君を愛しました",
  "ncode": "N3159FZ"
 },
 {
  "title": "ダンマスの嫁。",
  "ncode": "N2833FZ"
 },
 {
  "title": "2度転生した無能力者は平凡に暮らせなかった",
  "ncode": "N3178FZ"
 },
 {
  "title": "超越神の世界旅行",
  "ncode": "N3202FZ"
 },
 {
  "title": "二人の王子とその取り巻きに私刑されたら、過去に戻ったからクーデターする",
  "ncode": "N2982FZ"
 },
 {
  "title": "愛し子はスローライフをご所望です",
  "ncode": "N2499FZ"
 },
 {
  "title": "この罪に満たされる。",
  "ncode": "N2109FZ"
 },
 {
  "title": "精霊なしの僕は槍を持つ",
  "ncode": "N2286FZ"
 },
 {
  "title": "不死川雪路は殺される",
  "ncode": "N3258FZ"
 },
 {
  "title": "地球に出現したダンジョンを女子中学生が攻略する話",
  "ncode": "N2923FZ"
 },
 {
  "title": "オーバーラップ！！",
  "ncode": "N2835FZ"
 },
 {
  "title": "10分間の悪役令嬢　～悪役令嬢から始まる令嬢達のオムニバス～",
  "ncode": "N2385FZ"
 },
 {
  "title": "燃えるような刻の中で、青竜の歌を詠む",
  "ncode": "N2934FZ"
 },
 {
  "title": "うちの彼女(仮)が笑ってくれないので、とりあえずデレさせます！",
  "ncode": "N2780FZ"
 },
 {
  "title": "引退魔導士と普通の僕",
  "ncode": "N2849FZ"
 },
 {
  "title": "出会い求めてゲームしてたら異世界に迷い込んじゃった！",
  "ncode": "N3233FZ"
 },
 {
  "title": "フロンティア・ロード・オンライン ",
  "ncode": "N1983FZ"
 },
 {
  "title": "呪われ体質の公爵令嬢が悪堕ちしそうでしない",
  "ncode": "N2941FZ"
 },
 {
  "title": "魔道士拾いました",
  "ncode": "N3024FZ"
 },
 {
  "title": "メラバ",
  "ncode": "N3176FZ"
 },
 {
  "title": "自然哲学妄想ノート",
  "ncode": "N2865FZ"
 },
 {
  "title": "物理学",
  "ncode": "N2881FZ"
 },
 {
  "title": "猫に花束を",
  "ncode": "N3209FZ"
 },
 {
  "title": "クラスの双子と家族になりました",
  "ncode": "N3194FZ"
 },
 {
  "title": "黒い死神と異世界と ",
  "ncode": "N3108FZ"
 },
 {
  "title": "婚約破棄は、繰り返さないとダメですか？",
  "ncode": "N2950FZ"
 },
 {
  "title": "転生王族の異世界生活",
  "ncode": "N2991FZ"
 },
 {
  "title": "さくらちゃん",
  "ncode": "N3213FZ"
 },
 {
  "title": "ガチャ系召喚士さん、神引きする",
  "ncode": "N2896FZ"
 },
 {
  "title": "暗黒神、あるいは鋼のベルゼビュート",
  "ncode": "N1836FZ"
 },
 {
  "title": "双子術士転生",
  "ncode": "N3116FZ"
 },
 {
  "title": "桃太郎に「鬼がめちゃ強い。助けて」と言われたので、S級戦士の俺が倒しに行きます。",
  "ncode": "N3015FZ"
 },
 {
  "title": "異世界調査隊",
  "ncode": "N2857FZ"
 },
 {
  "title": "月のやまいぬ",
  "ncode": "N2821FZ"
 },
 {
  "title": "落第生が最強ガチャでやりたい放題！～実は無双スキル持ちでした～",
  "ncode": "N2513FZ"
 },
 {
  "title": "三人の漂着者　～軍規に反しない範囲で自由に生きます～",
  "ncode": "N2984FZ"
 },
 {
  "title": "追放された中年冒険者と死ねずの貴族令嬢の死を探す旅",
  "ncode": "N2996FZ"
 },
 {
  "title": "私が好きな本",
  "ncode": "N3052FZ"
 },
 {
  "title": "遊び人は賢者になれるって聞いたのに？",
  "ncode": "N3182FZ"
 },
 {
  "title": "槍の又左一代記",
  "ncode": "N3129FZ"
 },
 {
  "title": "カフェオレはエリクサー～喫茶店の常連客が地球を救う。どうやら私は錬金術師らしい～",
  "ncode": "N3167FZ"
 },
 {
  "title": "TSUKUYOMI　No.101 Fly me to the moon",
  "ncode": "N2816FZ"
 },
 {
  "title": "八割れ猫のはち 　～我が家に笑顔をくれた猫～",
  "ncode": "N3118FZ"
 },
 {
  "title": "リセマラの末に選ばれたのはありふれた職業でした",
  "ncode": "N3138FZ"
 },
 {
  "title": "超念の武闘姫",
  "ncode": "N3205FZ"
 },
 {
  "title": "下町異世界探偵 ２／フルスロットルで魔女は…",
  "ncode": "N2981FZ"
 },
 {
  "title": "青空の彼方にて",
  "ncode": "N3166FZ"
 },
 {
  "title": "マニアック・ベースボール",
  "ncode": "N3105FZ"
 },
 {
  "title": "幼馴染の美少女騎士を嫁にしたんだが、ヤンデレ予備軍で独占欲が強いのでハーレムは無理そうです。",
  "ncode": "N3087FZ"
 },
 {
  "title": "僕の可愛い婚約者の為ならば。",
  "ncode": "N2922FZ"
 },
 {
  "title": "異世界兄弟〜上位ランカーの兄弟は、異世界でも最強を目指します〜",
  "ncode": "N2983FZ"
 },
 {
  "title": "悪役令嬢の私が破滅を回避したせいで、かわりにヒロインが辺境伯の後妻に！？　寝覚めが悪いので阻止しようと思います ",
  "ncode": "N3094FZ"
 },
 {
  "title": "日本分裂",
  "ncode": "N3127FZ"
 },
 {
  "title": "A.D.１９９９　～逆襲のノストラダムス～",
  "ncode": "N3224FZ"
 },
 {
  "title": "弱小勇者と可憐なお姫様",
  "ncode": "N3179FZ"
 }
]